{
  "region_id": "LK-61-Ibbagamuwa",
  "generated_date": "2026-06-30",
  "weekly_features": [
    {
      "week": "2025-10-20",
      "rainfall": 150.0,
      "max_temp": 27.5143,
      "min_temp": 22.4714,
      "R_lag10": 21.5,
      "MT_lag16": 31.1667,
      "mT_lag13": 22.6429
    },
    {
      "week": "2025-10-27",
      "rainfall": 20.1,
      "max_temp": 30.3286,
      "min_temp": 23.2,
      "R_lag10": 5.9,
      "MT_lag16": 32.2,
      "mT_lag13": 23.8429
    },
    {
      "week": "2025-11-03",
      "rainfall": 28.2,
      "max_temp": 29.9714,
      "min_temp": 22.4571,
      "R_lag10": 28.3,
      "MT_lag16": 30.0714,
      "mT_lag13": 23.9571
    },
    {
      "week": "2025-11-10",
      "rainfall": 66.6,
      "max_temp": 29.4571,
      "min_temp": 22.3429,
      "R_lag10": 9.5,
      "MT_lag16": 27.6,
      "mT_lag13": 23.0857
    },
    {
      "week": "2025-11-17",
      "rainfall": 170.7,
      "max_temp": 29.3143,
      "min_temp": 22.6,
      "R_lag10": 48.8,
      "MT_lag16": 30.1714,
      "mT_lag13": 23.7286
    },
    {
      "week": "2025-11-24",
      "rainfall": 434.8,
      "max_temp": 24.7,
      "min_temp": 21.8429,
      "R_lag10": 39.9,
      "MT_lag16": 30.0429,
      "mT_lag13": 23.4857
    },
    {
      "week": "2025-12-01",
      "rainfall": 5.2,
      "max_temp": 29.7571,
      "min_temp": 21.8429,
      "R_lag10": 33.7,
      "MT_lag16": 29.7429,
      "mT_lag13": 24.1857
    },
    {
      "week": "2025-12-08",
      "rainfall": 32.3,
      "max_temp": 28.0143,
      "min_temp": 22.3143,
      "R_lag10": 26.2,
      "MT_lag16": 32.7143,
      "mT_lag13": 23.8571
    },
    {
      "week": "2025-12-15",
      "rainfall": 17.4,
      "max_temp": 27.9429,
      "min_temp": 22.3571,
      "R_lag10": 25.8,
      "MT_lag16": 31.9714,
      "mT_lag13": 23.7857
    },
    {
      "week": "2025-12-22",
      "rainfall": 2.8,
      "max_temp": 28.8286,
      "min_temp": 21.7857,
      "R_lag10": 161.6,
      "MT_lag16": 33.2429,
      "mT_lag13": 23.3
    },
    {
      "week": "2025-12-29",
      "rainfall": 41.6,
      "max_temp": 28.6714,
      "min_temp": 22.3571,
      "R_lag10": 150.0,
      "MT_lag16": 32.3429,
      "mT_lag13": 23.7143
    },
    {
      "week": "2026-01-05",
      "rainfall": 29.2,
      "max_temp": 26.9286,
      "min_temp": 21.7429,
      "R_lag10": 20.1,
      "MT_lag16": 30.3143,
      "mT_lag13": 23.1714
    },
    {
      "week": "2026-01-12",
      "rainfall": 13.1,
      "max_temp": 28.8571,
      "min_temp": 20.9429,
      "R_lag10": 28.2,
      "MT_lag16": 30.6714,
      "mT_lag13": 23.0286
    },
    {
      "week": "2026-01-19",
      "rainfall": 7.1,
      "max_temp": 29.2571,
      "min_temp": 19.2286,
      "R_lag10": 66.6,
      "MT_lag16": 32.9143,
      "mT_lag13": 22.4714
    },
    {
      "week": "2026-01-26",
      "rainfall": 25.3,
      "max_temp": 29.5143,
      "min_temp": 21.4286,
      "R_lag10": 170.7,
      "MT_lag16": 33.5286,
      "mT_lag13": 23.2
    },
    {
      "week": "2026-02-02",
      "rainfall": 26.7,
      "max_temp": 28.6857,
      "min_temp": 22.6857,
      "R_lag10": 434.8,
      "MT_lag16": 31.2429,
      "mT_lag13": 22.4571
    },
    {
      "week": "2026-02-09",
      "rainfall": 6.0,
      "max_temp": 29.3286,
      "min_temp": 21.5,
      "R_lag10": 5.2,
      "MT_lag16": 27.5143,
      "mT_lag13": 22.3429
    },
    {
      "week": "2026-02-16",
      "rainfall": 84.4,
      "max_temp": 27.9143,
      "min_temp": 22.1429,
      "R_lag10": 32.3,
      "MT_lag16": 30.3286,
      "mT_lag13": 22.6
    },
    {
      "week": "2026-02-23",
      "rainfall": 0.7,
      "max_temp": 31.4571,
      "min_temp": 20.6143,
      "R_lag10": 17.4,
      "MT_lag16": 29.9714,
      "mT_lag13": 21.8429
    },
    {
      "week": "2026-03-02",
      "rainfall": 4.1,
      "max_temp": 32.8857,
      "min_temp": 19.8714,
      "R_lag10": 2.8,
      "MT_lag16": 29.4571,
      "mT_lag13": 21.8429
    },
    {
      "week": "2026-03-09",
      "rainfall": 16.3,
      "max_temp": 33.9286,
      "min_temp": 21.7286,
      "R_lag10": 41.6,
      "MT_lag16": 29.3143,
      "mT_lag13": 22.3143
    },
    {
      "week": "2026-03-16",
      "rainfall": 22.0,
      "max_temp": 35.1429,
      "min_temp": 22.3571,
      "R_lag10": 29.2,
      "MT_lag16": 24.7,
      "mT_lag13": 22.3571
    },
    {
      "week": "2026-03-23",
      "rainfall": 2.3,
      "max_temp": 35.8571,
      "min_temp": 22.6857,
      "R_lag10": 13.1,
      "MT_lag16": 29.7571,
      "mT_lag13": 21.7857
    },
    {
      "week": "2026-03-30",
      "rainfall": 21.6,
      "max_temp": 34.6143,
      "min_temp": 23.2429,
      "R_lag10": 7.1,
      "MT_lag16": 28.0143,
      "mT_lag13": 22.3571
    },
    {
      "week": "2026-04-06",
      "rainfall": 16.0,
      "max_temp": 34.8571,
      "min_temp": 24.4143,
      "R_lag10": 25.3,
      "MT_lag16": 27.9429,
      "mT_lag13": 21.7429
    },
    {
      "week": "2026-04-13",
      "rainfall": 19.0,
      "max_temp": 34.1429,
      "min_temp": 23.7857,
      "R_lag10": 26.7,
      "MT_lag16": 28.8286,
      "mT_lag13": 20.9429
    },
    {
      "week": "2026-04-20",
      "rainfall": 35.4,
      "max_temp": 33.3,
      "min_temp": 23.7857,
      "R_lag10": 6.0,
      "MT_lag16": 28.6714,
      "mT_lag13": 19.2286
    },
    {
      "week": "2026-04-27",
      "rainfall": 26.4,
      "max_temp": 32.8143,
      "min_temp": 24.0714,
      "R_lag10": 84.4,
      "MT_lag16": 26.9286,
      "mT_lag13": 21.4286
    },
    {
      "week": "2026-05-04",
      "rainfall": 73.7,
      "max_temp": 31.9143,
      "min_temp": 24.1,
      "R_lag10": 0.7,
      "MT_lag16": 28.8571,
      "mT_lag13": 22.6857
    },
    {
      "week": "2026-05-11",
      "rainfall": 82.3,
      "max_temp": 29.1857,
      "min_temp": 23.6,
      "R_lag10": 4.1,
      "MT_lag16": 29.2571,
      "mT_lag13": 21.5
    },
    {
      "week": "2026-05-18",
      "rainfall": 15.5,
      "max_temp": 29.9857,
      "min_temp": 24.7714,
      "R_lag10": 16.3,
      "MT_lag16": 29.5143,
      "mT_lag13": 22.1429
    },
    {
      "week": "2026-05-25",
      "rainfall": 17.2,
      "max_temp": 30.5286,
      "min_temp": 24.8857,
      "R_lag10": 22.0,
      "MT_lag16": 28.6857,
      "mT_lag13": 20.6143
    },
    {
      "week": "2026-06-01",
      "rainfall": 29.5,
      "max_temp": 30.5429,
      "min_temp": 24.3571,
      "R_lag10": 2.3,
      "MT_lag16": 29.3286,
      "mT_lag13": 19.8714
    },
    {
      "week": "2026-06-08",
      "rainfall": 72.1,
      "max_temp": 28.5857,
      "min_temp": 23.8143,
      "R_lag10": 21.6,
      "MT_lag16": 27.9143,
      "mT_lag13": 21.7286
    },
    {
      "week": "2026-06-15",
      "rainfall": 20.7,
      "max_temp": 29.6286,
      "min_temp": 24.3286,
      "R_lag10": 16.0,
      "MT_lag16": 31.4571,
      "mT_lag13": 22.3571
    },
    {
      "week": "2026-06-22",
      "rainfall": 36.4,
      "max_temp": 29.4857,
      "min_temp": 23.9429,
      "R_lag10": 19.0,
      "MT_lag16": 32.8857,
      "mT_lag13": 22.6857
    },
    {
      "week": "2026-06-29",
      "rainfall": 4.8,
      "max_temp": 28.85,
      "min_temp": 24.25,
      "R_lag10": 35.4,
      "MT_lag16": 33.9286,
      "mT_lag13": 23.2429
    }
  ]
}